twisted/plugins/__init__.py
twisted/plugins/vncap_policy.py
twisted/plugins/vncap_proxy.py
vncap/__init__.py
vncap/control.py
vncap/ssh/__init__.py
vncap/ssh/protocol.py
vncap/vnc/__init__.py
vncap/vnc/d3des.py
vncap/vnc/factory.py
vncap/vnc/protocol.py
VNCAuthProxy-1.2.0.dist-info/METADATA
VNCAuthProxy-1.2.0.dist-info/WHEEL
VNCAuthProxy-1.2.0.dist-info/top_level.txt
VNCAuthProxy-1.2.0.dist-info/RECORD
