Metadata-Version: 2.1
Name: VNCAuthProxy
Version: 1.2.0
Summary: A Twisted-based VNC proxy
Home-page: https://github.com/osuosl/twisted_vncauthproxy
Author: Corbin Simpson, OSU Open Source Lab
Author-email: simpsoco@osuosl.org, pypi@osuosl.org
License: GPL2
Platform: UNKNOWN
Requires-Python: <3.0
Requires-Dist: Twisted (<20.4.0,>=10.2.0)
Requires-Dist: txWS (==0.9.1)
Requires-Dist: pyopenssl (<22.0.0)
Requires-Dist: cryptography (<3.4)
Requires-Dist: idna (<3.0)
Requires-Dist: pyasn1
Requires-Dist: PyHamcrest (<2.0)
Requires-Dist: service-identity
Requires-Dist: typing (<3.10)
